xmh_utils/__init__.py
xmh_utils/o_utils.py
xmh_utils-0.0.2.dist-info/METADATA
xmh_utils-0.0.2.dist-info/WHEEL
xmh_utils-0.0.2.dist-info/top_level.txt
xmh_utils-0.0.2.dist-info/RECORD
