Metadata-Version: 2.1
Name: xmh-utils
Version: 0.0.2
Summary: Gadgets you might use
Home-page: UNKNOWN
Author: MengX
Author-email: xmh136835951@163.com
License: apache 3.0
Platform: UNKNOWN
